tests/__init__.py
tests/test_checker.py
tests/test_kafka_producer.py
web_monitor/__init__.py
web_monitor/__main__.py
web_monitor/checker.py
web_monitor/kafka_producer.py
web_monitor_aiven-0.2.1.dist-info/METADATA
web_monitor_aiven-0.2.1.dist-info/WHEEL
web_monitor_aiven-0.2.1.dist-info/entry_points.txt
web_monitor_aiven-0.2.1.dist-info/top_level.txt
web_monitor_aiven-0.2.1.dist-info/RECORD
