Metadata-Version: 2.1
Name: web-monitor-aiven
Version: 0.2.1
Summary: A scalable web monitor application for Aiven Kafka
Home-page: UNKNOWN
License: UNKNOWN
Platform: UNKNOWN
Classifier: Programming Language :: Python :: 3
Classifier: License :: OSI Approved :: MIT License
Classifier: Operating System :: OS Independent
Requires-Python: >=3.6
Requires-Dist: requests
Requires-Dist: kafka-python
Requires-Dist: pyyaml
